flask_firewall/__init__.py
flask_firewall/firewall.py
flask_firewall-0.1.0.dist-info/licenses/LICENSE
flask_firewall-0.1.0.dist-info/METADATA
flask_firewall-0.1.0.dist-info/WHEEL
flask_firewall-0.1.0.dist-info/top_level.txt
flask_firewall-0.1.0.dist-info/RECORD
