Metadata-Version: 2.4
Name: flask_firewall
Version: 0.1.0
Summary: A comprehensive firewall middleware for Flask applications
Home-page: https://github.com/Ishanoshada/flask_firewall
Author: Ishan Oshada
Author-email: ic31908@gmail.com
License: MIT
Keywords: flask firewall security waf recaptcha rate-limiting xss
Classifier: Programming Language :: Python :: 3
Classifier: Programming Language :: Python :: 3.8
Classifier: Programming Language :: Python :: 3.9
Classifier: Programming Language :: Python :: 3.10
Classifier: Programming Language :: Python :: 3.11
Classifier: License :: OSI Approved :: MIT License
Classifier: Operating System :: OS Independent
Classifier: Framework :: Flask
Classifier: Intended Audience :: Developers
Classifier: Topic :: Security
Requires-Python: >=3.8
License-File: LICENSE
Requires-Dist: Flask>=2.0.0
Requires-Dist: requests>=2.25.0
Requires-Dist: pytz>=2021.1
Dynamic: author
Dynamic: author-email
Dynamic: classifier
Dynamic: description
Dynamic: description-content-type
Dynamic: home-page
Dynamic: keywords
Dynamic: license
Dynamic: license-file
Dynamic: requires-dist
Dynamic: requires-python
Dynamic: summary
